json_logic/__init__.py
json_logic/__main__.py
json_logic/apply.py
json_logic/builtins.py
json_logic/extras.py
json_logic/types.py
json_logic/cert_logic/__init__.py
json_logic/cert_logic/__main__.py
json_logic/cert_logic/apply.py
json_logic/cert_logic/builtins.py
json_logic/cert_logic/extras.py
panzi_json_logic-1.0.0.dist-info/LICENSE
panzi_json_logic-1.0.0.dist-info/METADATA
panzi_json_logic-1.0.0.dist-info/WHEEL
panzi_json_logic-1.0.0.dist-info/top_level.txt
panzi_json_logic-1.0.0.dist-info/RECORD
