Metadata-Version: 2.1
Name: panzi-json-logic
Version: 1.0.0
Summary: Pure Python 3 JsonLogic and CertLogic implementation.
Home-page: https://github.com/panzi/panzi-json-logic
Author: Mathias Panzenböck
License: UNKNOWN
Project-URL: Bug Tarcker, https://github.com/panzi/panzi-json-logic/issues
Platform: UNKNOWN
Classifier: Programming Language :: Python :: 3
Classifier: License :: OSI Approved :: MIT License
Classifier: Operating System :: OS Independent
Requires-Python: >=3.6
License-File: LICENSE
